gonchaya/__init__.py
gonchaya/__init__.pyi
gonchaya/cli.py
gonchaya/debug.py
gonchaya/debug.pyi
gonchaya/main.py
gonchaya/refactor_phases.py
gonchaya/superfast.py
gonchaya/superfast.pyi
gonchaya-0.0.10.dist-info/licenses/LICENSE
gonchaya-0.0.10.dist-info/METADATA
gonchaya-0.0.10.dist-info/WHEEL
gonchaya-0.0.10.dist-info/entry_points.txt
gonchaya-0.0.10.dist-info/top_level.txt
gonchaya-0.0.10.dist-info/RECORD
