Metadata-Version: 2.4
Name: gonchaya
Version: 0.0.10
Author-email: Alexander Firsov <gonchaya@gifara.ru>
License: Copyright (c) 2025 Alexander Firsov <gonchaya@gifara.ru>. All rights reserved.
Project-URL: Repository, https://github.com/Alexander-Firsov/gonchaya
Project-URL: Homepage, https://github.com/Alexander-Firsov/gonchaya
Classifier: Development Status :: 1 - Planning
Classifier: License :: OSI Approved :: BSD License
Classifier: Programming Language :: Python :: 3
Classifier: Programming Language :: Python :: 3.12
Classifier: Operating System :: OS Independent
Classifier: Natural Language :: English
Classifier: Natural Language :: Russian
Requires-Python: >=3.12
License-File: LICENSE
Requires-Dist: colorama
Provides-Extra: test
Requires-Dist: pytest; extra == "test"
Provides-Extra: dev
Requires-Dist: black; extra == "dev"
Requires-Dist: pylint; extra == "dev"
Dynamic: license-file
